{
  "gitSyncId": "69ea04ccf4cb327f11981332_f8522ee1-0442-4d86-90d8-9d3930f561ea",
  "id": "Configuración_getCategoriaDropdown",
  "pluginId": "mysql-plugin",
  "pluginType": "DB",
  "unpublishedAction": {
    "actionConfiguration": {
      "body": "SELECT id_categoria as value, \nnombre_categoria as label \nFROM categorias_capacitaciones;\n",
      "encodeParamsToggle": true,
      "paginationType": "NONE",
      "pluginSpecifiedTemplates": [
        {
          "value": true
        }
      ],
      "timeoutInMillisecond": 10000
    },
    "confirmBeforeExecute": false,
    "datasource": {
      "id": "agenda_tecnicos",
      "isAutoGenerated": false,
      "name": "agenda_tecnicos",
      "pluginId": "mysql-plugin"
    },
    "dynamicBindingPathList": [],
    "name": "getCategoriaDropdown",
    "pageId": "Configuración",
    "runBehaviour": "AUTOMATIC",
    "userSetOnLoad": false
  }
}