{
  "animateLoading": true,
  "borderRadius": "{{appsmith.theme.borderRadius.appBorderRadius}}",
  "bottomRow": 4,
  "dynamicBindingPathList": [
    {
      "key": "truncateButtonColor"
    },
    {
      "key": "fontFamily"
    },
    {
      "key": "borderRadius"
    }
  ],
  "dynamicHeight": "FIXED",
  "dynamicTriggerPathList": [],
  "fontFamily": "{{appsmith.theme.fontFamily.appFont}}",
  "fontSize": "1rem",
  "fontStyle": "BOLD",
  "isLoading": false,
  "isVisible": true,
  "key": "6nbaygcp8c",
  "leftColumn": 1,
  "maxDynamicHeight": 9000,
  "minDynamicHeight": 4,
  "minWidth": 450,
  "mobileBottomRow": 7,
  "mobileLeftColumn": 7,
  "mobileRightColumn": 23,
  "mobileTopRow": 3,
  "needsErrorInfo": false,
  "overflow": "NONE",
  "parentColumnSpace": 6.9375,
  "parentId": "0onpblimpe",
  "parentRowSpace": 10,
  "renderMode": "CANVAS",
  "responsiveBehavior": "fill",
  "rightColumn": 41,
  "shouldScrollContents": true,
  "shouldTruncate": false,
  "text": "Editar información del Personal",
  "textAlign": "LEFT",
  "textColor": "#231F20",
  "topRow": 0,
  "truncateButtonColor": "{{appsmith.theme.colors.primaryColor}}",
  "type": "TEXT_WIDGET",
  "version": 1,
  "widgetId": "kbi3thlpo3",
  "widgetName": "TextTit"
}