{
  "gitSyncId": "697c8f869bb6771f6fd6defb_3b836a0e-fb37-4b1e-a1ef-8addfbd39a98",
  "id": "Horario_ValidacionJS.validarDiaCorrecto",
  "pluginId": "js-plugin",
  "pluginType": "JS",
  "unpublishedAction": {
    "actionConfiguration": {
      "encodeParamsToggle": true,
      "jsArguments": [
        {
          "name": "fechaSeleccionada"
        },
        {
          "name": "diaAgenda"
        }
      ],
      "paginationType": "NONE",
      "timeoutInMillisecond": 10000
    },
    "collectionId": "Horario_ValidacionJS",
    "confirmBeforeExecute": false,
    "datasource": {
      "isAutoGenerated": false,
      "name": "UNUSED_DATASOURCE",
      "pluginId": "js-plugin"
    },
    "dynamicBindingPathList": [
      {
        "key": "body"
      }
    ],
    "fullyQualifiedName": "ValidacionJS.validarDiaCorrecto",
    "name": "validarDiaCorrecto",
    "pageId": "Horario",
    "runBehaviour": "MANUAL",
    "userSetOnLoad": false
  }
}